{
  "created_by": {
    "avatar": "https://img.qwps.cn/1249174163?imageMogr2/thumbnail/180x180!&k=1733060992276249955",
    "company_id": "0",
    "id": "1249174163",
    "name": "君言",
    "type": "user"
  },
  "ctime": 1755431361,
  "drive_id": "2581401869",
  "ext_attrs": [
    {
      "name": "secure_guid",
      "value": ""
    },
    {
      "name": "protected",
      "value": "false"
    }
  ],
  "hash": {
    "sum": "051c3fed529b679d71e9203733ec909c8b3fa2d8",
    "type": "sha1"
  },
  "id": "AgB4CbCJArMo8E4ueMiD1xjqjdxhmHsFr",
  "link_id": "cpfOoKPCu9xv",
  "link_url": "https://www.kdocs.cn/l/cpfOoKPCu9xv",
  "modified_by": {
    "avatar": "https://img.qwps.cn/1249174163?imageMogr2/thumbnail/180x180!&k=1733060992276249955",
    "company_id": "0",
    "id": "1249174163",
    "name": "君言",
    "type": "user"
  },
  "mtime": 1755431361,
  "name": "162：“跨年群”可能的变现形式.otl",
  "parent_id": "E5CAmuwtbxM6HRY9iuoFrxxa4zFr6Z2UB",
  "permission": {
    "comment": false,
    "copy": false,
    "copy_content": false,
    "delete": false,
    "download": false,
    "history": false,
    "list": true,
    "move": false,
    "new_empty": false,
    "perm_ctl": false,
    "preview": true,
    "print": false,
    "rename": false,
    "saveas": false,
    "secret": false,
    "share": false,
    "update": false,
    "upload": false
  },
  "shared": false,
  "size": 1491172,
  "type": "file",
  "version": 1,
  "path": "单条分享/162：“跨年群”可能的变现形式.otl"
}